{
  "updated": "2026/07/01 11:17",
  "date": "2026/07/01",
  "data": [
    {
      "日期": "2026/07/01",
      "CB代號": "811211",
      "CB名稱": "至上11",
      "外資_買張": 0,
      "外資_賣張": 0,
      "外資_買賣超": 0,
      "投信_買張": 0,
      "投信_賣張": 0,
      "投信_買賣超": 0,
      "自營_買張": 1537,
      "自營_賣張": 181,
      "自營_買賣超": 1356,
      "三大法人合計買賣超": 1356,
      "買超方向": "↑買超"
    },
    {
      "日期": "2026/07/01",
      "CB代號": "52892",
      "CB名稱": "宜鼎二",
      "外資_買張": 50,
      "外資_賣張": 0,
      "外資_買賣超": 50,
      "投信_買張": 0,
      "投信_賣張": 0,
      "投信_買賣超": 0,
      "自營_買張": 837,
      "自營_賣張": 220,
      "自營_買賣超": 617,
      "三大法人合計買賣超": 667,
      "買超方向": "↑買超"
    },
    {
      "日期": "2026/07/01",
      "CB代號": "62236",
      "CB名稱": "旺矽六",
      "外資_買張": 0,
      "外資_賣張": 0,
      "外資_買賣超": 0,
      "投信_買張": 0,
      "投信_賣張": 0,
      "投信_買賣超": 0,
      "自營_買張": 571,
      "自營_賣張": 212,
      "自營_買賣超": 359,
      "三大法人合計買賣超": 359,
      "買超方向": "↑買超"
    },
    {
      "日期": "2026/07/01",
      "CB代號": "37171",
      "CB名稱": "聯嘉投控一",
      "外資_買張": 0,
      "外資_賣張": 0,
      "外資_買賣超": 0,
      "投信_買張": 0,
      "投信_賣張": 0,
      "投信_買賣超": 0,
      "自營_買張": 423,
      "自營_賣張": 303,
      "自營_買賣超": 120,
      "三大法人合計買賣超": 120,
      "買超方向": "↑買超"
    },
    {
      "日期": "2026/07/01",
      "CB代號": "622010",
      "CB名稱": "岳豐十",
      "外資_買張": 0,
      "外資_賣張": 0,
      "外資_買賣超": 0,
      "投信_買張": 0,
      "投信_賣張": 0,
      "投信_買賣超": 0,
      "自營_買張": 101,
      "自營_賣張": 18,
      "自營_買賣超": 83,
      "三大法人合計買賣超": 83,
      "買超方向": "↑買超"
    },
    {
      "日期": "2026/07/01",
      "CB代號": "65101",
      "CB名稱": "精測一",
      "外資_買張": 0,
      "外資_賣張": 0,
      "外資_買賣超": 0,
      "投信_買張": 0,
      "投信_賣張": 0,
      "投信_買賣超": 0,
      "自營_買張": 148,
      "自營_賣張": 68,
      "自營_買賣超": 80,
      "三大法人合計買賣超": 80,
      "買超方向": "↑買超"
    },
    {
      "日期": "2026/07/01",
      "CB代號": "65463",
      "CB名稱": "正基三",
      "外資_買張": 0,
      "外資_賣張": 0,
      "外資_買賣超": 0,
      "投信_買張": 0,
      "投信_賣張": 0,
      "投信_買賣超": 0,
      "自營_買張": 76,
      "自營_賣張": 0,
      "自營_買賣超": 76,
      "三大法人合計買賣超": 76,
      "買超方向": "↑買超"
    },
    {
      "日期": "2026/07/01",
      "CB代號": "65096",
      "CB名稱": "聚和六",
      "外資_買張": 0,
      "外資_賣張": 0,
      "外資_買賣超": 0,
      "投信_買張": 0,
      "投信_賣張": 0,
      "投信_買賣超": 0,
      "自營_買張": 195,
      "自營_賣張": 158,
      "自營_買賣超": 37,
      "三大法人合計買賣超": 37,
      "買超方向": "↑買超"
    },
    {
      "日期": "2026/07/01",
      "CB代號": "22331",
      "CB名稱": "宇隆一",
      "外資_買張": 0,
      "外資_賣張": 0,
      "外資_買賣超": 0,
      "投信_買張": 0,
      "投信_賣張": 0,
      "投信_買賣超": 0,
      "自營_買張": 102,
      "自營_賣張": 68,
      "自營_買賣超": 34,
      "三大法人合計買賣超": 34,
      "買超方向": "↑買超"
    },
    {
      "日期": "2026/07/01",
      "CB代號": "32943",
      "CB名稱": "英濟三",
      "外資_買張": 0,
      "外資_賣張": 0,
      "外資_買賣超": 0,
      "投信_買張": 0,
      "投信_賣張": 0,
      "投信_買賣超": 0,
      "自營_買張": 35,
      "自營_賣張": 4,
      "自營_買賣超": 31,
      "三大法人合計買賣超": 31,
      "買超方向": "↑買超"
    },
    {
      "日期": "2026/07/01",
      "CB代號": "68621",
      "CB名稱": "三集瑞一KY",
      "外資_買張": 0,
      "外資_賣張": 0,
      "外資_買賣超": 0,
      "投信_買張": 0,
      "投信_賣張": 0,
      "投信_買賣超": 0,
      "自營_買張": 30,
      "自營_賣張": 0,
      "自營_買賣超": 30,
      "三大法人合計買賣超": 30,
      "買超方向": "↑買超"
    },
    {
      "日期": "2026/07/01",
      "CB代號": "41903",
      "CB名稱": "佐登三KY",
      "外資_買張": 0,
      "外資_賣張": 0,
      "外資_買賣超": 0,
      "投信_買張": 0,
      "投信_賣張": 0,
      "投信_買賣超": 0,
      "自營_買張": 28,
      "自營_賣張": 0,
      "自營_買賣超": 28,
      "三大法人合計買賣超": 28,
      "買超方向": "↑買超"
    },
    {
      "日期": "2026/07/01",
      "CB代號": "67531",
      "CB名稱": "龍德造船一",
      "外資_買張": 0,
      "外資_賣張": 0,
      "外資_買賣超": 0,
      "投信_買張": 0,
      "投信_賣張": 0,
      "投信_買賣超": 0,
      "自營_買張": 89,
      "自營_賣張": 64,
      "自營_買賣超": 25,
      "三大法人合計買賣超": 25,
      "買超方向": "↑買超"
    },
    {
      "日期": "2026/07/01",
      "CB代號": "23291",
      "CB名稱": "華泰一",
      "外資_買張": 0,
      "外資_賣張": 0,
      "外資_買賣超": 0,
      "投信_買張": 0,
      "投信_賣張": 0,
      "投信_買賣超": 0,
      "自營_買張": 105,
      "自營_賣張": 80,
      "自營_買賣超": 25,
      "三大法人合計買賣超": 25,
      "買超方向": "↑買超"
    },
    {
      "日期": "2026/07/01",
      "CB代號": "34913",
      "CB名稱": "昇達科三",
      "外資_買張": 0,
      "外資_賣張": 0,
      "外資_買賣超": 0,
      "投信_買張": 35,
      "投信_賣張": 0,
      "投信_買賣超": 35,
      "自營_買張": 65,
      "自營_賣張": 77,
      "自營_買賣超": -12,
      "三大法人合計買賣超": 23,
      "買超方向": "↑買超"
    },
    {
      "日期": "2026/07/01",
      "CB代號": "65914",
      "CB名稱": "動力四KY",
      "外資_買張": 0,
      "外資_賣張": 0,
      "外資_買賣超": 0,
      "投信_買張": 0,
      "投信_賣張": 0,
      "投信_買賣超": 0,
      "自營_買張": 20,
      "自營_賣張": 0,
      "自營_買賣超": 20,
      "三大法人合計買賣超": 20,
      "買超方向": "↑買超"
    },
    {
      "日期": "2026/07/01",
      "CB代號": "33247",
      "CB名稱": "雙鴻七",
      "外資_買張": 0,
      "外資_賣張": 0,
      "外資_買賣超": 0,
      "投信_買張": 0,
      "投信_賣張": 0,
      "投信_買賣超": 0,
      "自營_買張": 60,
      "自營_賣張": 44,
      "自營_買賣超": 16,
      "三大法人合計買賣超": 16,
      "買超方向": "↑買超"
    },
    {
      "日期": "2026/07/01",
      "CB代號": "54391",
      "CB名稱": "高技一",
      "外資_買張": 0,
      "外資_賣張": 0,
      "外資_買賣超": 0,
      "投信_買張": 0,
      "投信_賣張": 0,
      "投信_買賣超": 0,
      "自營_買張": 33,
      "自營_賣張": 20,
      "自營_買賣超": 13,
      "三大法人合計買賣超": 13,
      "買超方向": "↑買超"
    },
    {
      "日期": "2026/07/01",
      "CB代號": "17172",
      "CB名稱": "長興二",
      "外資_買張": 0,
      "外資_賣張": 0,
      "外資_買賣超": 0,
      "投信_買張": 0,
      "投信_賣張": 0,
      "投信_買賣超": 0,
      "自營_買張": 59,
      "自營_賣張": 46,
      "自營_買賣超": 13,
      "三大法人合計買賣超": 13,
      "買超方向": "↑買超"
    },
    {
      "日期": "2026/07/01",
      "CB代號": "62822",
      "CB名稱": "康舒二",
      "外資_買張": 0,
      "外資_賣張": 0,
      "外資_買賣超": 0,
      "投信_買張": 0,
      "投信_賣張": 0,
      "投信_買賣超": 0,
      "自營_買張": 33,
      "自營_賣張": 21,
      "自營_買賣超": 12,
      "三大法人合計買賣超": 12,
      "買超方向": "↑買超"
    },
    {
      "日期": "2026/07/01",
      "CB代號": "45031",
      "CB名稱": "金雨一",
      "外資_買張": 0,
      "外資_賣張": 0,
      "外資_買賣超": 0,
      "投信_買張": 0,
      "投信_賣張": 0,
      "投信_買賣超": 0,
      "自營_買張": 35,
      "自營_賣張": 23,
      "自營_買賣超": 12,
      "三大法人合計買賣超": 12,
      "買超方向": "↑買超"
    },
    {
      "日期": "2026/07/01",
      "CB代號": "36173",
      "CB名稱": "碩天三",
      "外資_買張": 0,
      "外資_賣張": 0,
      "外資_買賣超": 0,
      "投信_買張": 0,
      "投信_賣張": 0,
      "投信_買賣超": 0,
      "自營_買張": 18,
      "自營_賣張": 6,
      "自營_買賣超": 12,
      "三大法人合計買賣超": 12,
      "買超方向": "↑買超"
    },
    {
      "日期": "2026/07/01",
      "CB代號": "30454",
      "CB名稱": "台灣大四",
      "外資_買張": 0,
      "外資_賣張": 0,
      "外資_買賣超": 0,
      "投信_買張": 0,
      "投信_賣張": 0,
      "投信_買賣超": 0,
      "自營_買張": 63,
      "自營_賣張": 51,
      "自營_買賣超": 12,
      "三大法人合計買賣超": 12,
      "買超方向": "↑買超"
    },
    {
      "日期": "2026/07/01",
      "CB代號": "45641",
      "CB名稱": "元翎一",
      "外資_買張": 0,
      "外資_賣張": 0,
      "外資_買賣超": 0,
      "投信_買張": 0,
      "投信_賣張": 0,
      "投信_買賣超": 0,
      "自營_買張": 10,
      "自營_賣張": 0,
      "自營_買賣超": 10,
      "三大法人合計買賣超": 10,
      "買超方向": "↑買超"
    },
    {
      "日期": "2026/07/01",
      "CB代號": "82711",
      "CB名稱": "宇瞻一",
      "外資_買張": 0,
      "外資_賣張": 0,
      "外資_買賣超": 0,
      "投信_買張": 0,
      "投信_賣張": 0,
      "投信_買賣超": 0,
      "自營_買張": 54,
      "自營_賣張": 45,
      "自營_買賣超": 9,
      "三大法人合計買賣超": 9,
      "買超方向": "↑買超"
    },
    {
      "日期": "2026/07/01",
      "CB代號": "36806",
      "CB名稱": "家登六",
      "外資_買張": 0,
      "外資_賣張": 0,
      "外資_買賣超": 0,
      "投信_買張": 0,
      "投信_賣張": 0,
      "投信_買賣超": 0,
      "自營_買張": 295,
      "自營_賣張": 286,
      "自營_買賣超": 9,
      "三大法人合計買賣超": 9,
      "買超方向": "↑買超"
    },
    {
      "日期": "2026/07/01",
      "CB代號": "82103",
      "CB名稱": "勤誠三",
      "外資_買張": 0,
      "外資_賣張": 0,
      "外資_買賣超": 0,
      "投信_買張": 0,
      "投信_賣張": 6,
      "投信_買賣超": -6,
      "自營_買張": 42,
      "自營_賣張": 28,
      "自營_買賣超": 14,
      "三大法人合計買賣超": 8,
      "買超方向": "↑買超"
    },
    {
      "日期": "2026/07/01",
      "CB代號": "66034",
      "CB名稱": "富強鑫四",
      "外資_買張": 0,
      "外資_賣張": 0,
      "外資_買賣超": 0,
      "投信_買張": 0,
      "投信_賣張": 0,
      "投信_買賣超": 0,
      "自營_買張": 12,
      "自營_賣張": 5,
      "自營_買賣超": 7,
      "三大法人合計買賣超": 7,
      "買超方向": "↑買超"
    },
    {
      "日期": "2026/07/01",
      "CB代號": "54501",
      "CB名稱": "南良一",
      "外資_買張": 0,
      "外資_賣張": 0,
      "外資_買賣超": 0,
      "投信_買張": 0,
      "投信_賣張": 0,
      "投信_買賣超": 0,
      "自營_買張": 16,
      "自營_賣張": 9,
      "自營_買賣超": 7,
      "三大法人合計買賣超": 7,
      "買超方向": "↑買超"
    },
    {
      "日期": "2026/07/01",
      "CB代號": "33246",
      "CB名稱": "雙鴻六",
      "外資_買張": 0,
      "外資_賣張": 0,
      "外資_買賣超": 0,
      "投信_買張": 3,
      "投信_賣張": 0,
      "投信_買賣超": 3,
      "自營_買張": 44,
      "自營_賣張": 40,
      "自營_買賣超": 4,
      "三大法人合計買賣超": 7,
      "買超方向": "↑買超"
    },
    {
      "日期": "2026/07/01",
      "CB代號": "24673",
      "CB名稱": "志聖三",
      "外資_買張": 0,
      "外資_賣張": 0,
      "外資_買賣超": 0,
      "投信_買張": 0,
      "投信_賣張": 0,
      "投信_買賣超": 0,
      "自營_買張": 16,
      "自營_賣張": 9,
      "自營_買賣超": 7,
      "三大法人合計買賣超": 7,
      "買超方向": "↑買超"
    },
    {
      "日期": "2026/07/01",
      "CB代號": "22472",
      "CB名稱": "汎德永業二",
      "外資_買張": 0,
      "外資_賣張": 0,
      "外資_買賣超": 0,
      "投信_買張": 0,
      "投信_賣張": 0,
      "投信_買賣超": 0,
      "自營_買張": 22,
      "自營_賣張": 15,
      "自營_買賣超": 7,
      "三大法人合計買賣超": 7,
      "買超方向": "↑買超"
    },
    {
      "日期": "2026/07/01",
      "CB代號": "47721",
      "CB名稱": "台特化一",
      "外資_買張": 0,
      "外資_賣張": 0,
      "外資_買賣超": 0,
      "投信_買張": 0,
      "投信_賣張": 0,
      "投信_買賣超": 0,
      "自營_買張": 35,
      "自營_賣張": 29,
      "自營_買賣超": 6,
      "三大法人合計買賣超": 6,
      "買超方向": "↑買超"
    },
    {
      "日期": "2026/07/01",
      "CB代號": "35872",
      "CB名稱": "閎康二",
      "外資_買張": 0,
      "外資_賣張": 0,
      "外資_買賣超": 0,
      "投信_買張": 0,
      "投信_賣張": 0,
      "投信_買賣超": 0,
      "自營_買張": 26,
      "自營_賣張": 20,
      "自營_買賣超": 6,
      "三大法人合計買賣超": 6,
      "買超方向": "↑買超"
    },
    {
      "日期": "2026/07/01",
      "CB代號": "30371",
      "CB名稱": "欣興一",
      "外資_買張": 0,
      "外資_賣張": 0,
      "外資_買賣超": 0,
      "投信_買張": 0,
      "投信_賣張": 4,
      "投信_買賣超": -4,
      "自營_買張": 13,
      "自營_賣張": 3,
      "自營_買賣超": 10,
      "三大法人合計買賣超": 6,
      "買超方向": "↑買超"
    },
    {
      "日期": "2026/07/01",
      "CB代號": "66721",
      "CB名稱": "騰輝電子一KY",
      "外資_買張": 0,
      "外資_賣張": 0,
      "外資_買賣超": 0,
      "投信_買張": 0,
      "投信_賣張": 0,
      "投信_買賣超": 0,
      "自營_買張": 5,
      "自營_賣張": 0,
      "自營_買賣超": 5,
      "三大法人合計買賣超": 5,
      "買超方向": "↑買超"
    },
    {
      "日期": "2026/07/01",
      "CB代號": "36805",
      "CB名稱": "家登五",
      "外資_買張": 0,
      "外資_賣張": 0,
      "外資_買賣超": 0,
      "投信_買張": 0,
      "投信_賣張": 0,
      "投信_買賣超": 0,
      "自營_買張": 17,
      "自營_賣張": 12,
      "自營_買賣超": 5,
      "三大法人合計買賣超": 5,
      "買超方向": "↑買超"
    },
    {
      "日期": "2026/07/01",
      "CB代號": "80282",
      "CB名稱": "昇陽半導體二",
      "外資_買張": 0,
      "外資_賣張": 0,
      "外資_買賣超": 0,
      "投信_買張": 0,
      "投信_賣張": 0,
      "投信_買賣超": 0,
      "自營_買張": 4,
      "自營_賣張": 0,
      "自營_買賣超": 4,
      "三大法人合計買賣超": 4,
      "買超方向": "↑買超"
    },
    {
      "日期": "2026/07/01",
      "CB代號": "68401",
      "CB名稱": "東研信超一",
      "外資_買張": 0,
      "外資_賣張": 0,
      "外資_買賣超": 0,
      "投信_買張": 0,
      "投信_賣張": 0,
      "投信_買賣超": 0,
      "自營_買張": 4,
      "自營_賣張": 0,
      "自營_買賣超": 4,
      "三大法人合計買賣超": 4,
      "買超方向": "↑買超"
    },
    {
      "日期": "2026/07/01",
      "CB代號": "47602",
      "CB名稱": "勤凱二",
      "外資_買張": 0,
      "外資_賣張": 0,
      "外資_買賣超": 0,
      "投信_買張": 0,
      "投信_賣張": 0,
      "投信_買賣超": 0,
      "自營_買張": 4,
      "自營_賣張": 0,
      "自營_買賣超": 4,
      "三大法人合計買賣超": 4,
      "買超方向": "↑買超"
    },
    {
      "日期": "2026/07/01",
      "CB代號": "41239",
      "CB名稱": "晟德九",
      "外資_買張": 0,
      "外資_賣張": 0,
      "外資_買賣超": 0,
      "投信_買張": 0,
      "投信_賣張": 0,
      "投信_買賣超": 0,
      "自營_買張": 4,
      "自營_賣張": 0,
      "自營_買賣超": 4,
      "三大法人合計買賣超": 4,
      "買超方向": "↑買超"
    },
    {
      "日期": "2026/07/01",
      "CB代號": "75562",
      "CB名稱": "意德士二",
      "外資_買張": 0,
      "外資_賣張": 0,
      "外資_買賣超": 0,
      "投信_買張": 0,
      "投信_賣張": 0,
      "投信_買賣超": 0,
      "自營_買張": 3,
      "自營_賣張": 0,
      "自營_買賣超": 3,
      "三大法人合計買賣超": 3,
      "買超方向": "↑買超"
    },
    {
      "日期": "2026/07/01",
      "CB代號": "68211",
      "CB名稱": "聯寶一",
      "外資_買張": 0,
      "外資_賣張": 0,
      "外資_買賣超": 0,
      "投信_買張": 0,
      "投信_賣張": 0,
      "投信_買賣超": 0,
      "自營_買張": 4,
      "自營_賣張": 1,
      "自營_買賣超": 3,
      "三大法人合計買賣超": 3,
      "買超方向": "↑買超"
    },
    {
      "日期": "2026/07/01",
      "CB代號": "65472",
      "CB名稱": "高端疫苗二",
      "外資_買張": 0,
      "外資_賣張": 0,
      "外資_買賣超": 0,
      "投信_買張": 0,
      "投信_賣張": 0,
      "投信_買賣超": 0,
      "自營_買張": 4,
      "自營_賣張": 1,
      "自營_買賣超": 3,
      "三大法人合計買賣超": 3,
      "買超方向": "↑買超"
    },
    {
      "日期": "2026/07/01",
      "CB代號": "47393",
      "CB名稱": "康普三",
      "外資_買張": 0,
      "外資_賣張": 0,
      "外資_買賣超": 0,
      "投信_買張": 0,
      "投信_賣張": 0,
      "投信_買賣超": 0,
      "自營_買張": 33,
      "自營_賣張": 30,
      "自營_買賣超": 3,
      "三大法人合計買賣超": 3,
      "買超方向": "↑買超"
    },
    {
      "日期": "2026/07/01",
      "CB代號": "41237",
      "CB名稱": "晟德七",
      "外資_買張": 0,
      "外資_賣張": 0,
      "外資_買賣超": 0,
      "投信_買張": 0,
      "投信_賣張": 0,
      "投信_買賣超": 0,
      "自營_買張": 3,
      "自營_賣張": 0,
      "自營_買賣超": 3,
      "三大法人合計買賣超": 3,
      "買超方向": "↑買超"
    },
    {
      "日期": "2026/07/01",
      "CB代號": "31312",
      "CB名稱": "弘塑二",
      "外資_買張": 0,
      "外資_賣張": 0,
      "外資_買賣超": 0,
      "投信_買張": 0,
      "投信_賣張": 0,
      "投信_買賣超": 0,
      "自營_買張": 10,
      "自營_賣張": 7,
      "自營_買賣超": 3,
      "三大法人合計買賣超": 3,
      "買超方向": "↑買超"
    },
    {
      "日期": "2026/07/01",
      "CB代號": "24395",
      "CB名稱": "美律五",
      "外資_買張": 0,
      "外資_賣張": 0,
      "外資_買賣超": 0,
      "投信_買張": 0,
      "投信_賣張": 0,
      "投信_買賣超": 0,
      "自營_買張": 4,
      "自營_賣張": 1,
      "自營_買賣超": 3,
      "三大法人合計買賣超": 3,
      "買超方向": "↑買超"
    },
    {
      "日期": "2026/07/01",
      "CB代號": "140202",
      "CB名稱": "遠東新E2永",
      "外資_買張": 0,
      "外資_賣張": 0,
      "外資_買賣超": 0,
      "投信_買張": 0,
      "投信_賣張": 0,
      "投信_買賣超": 0,
      "自營_買張": 3,
      "自營_賣張": 0,
      "自營_買賣超": 3,
      "三大法人合計買賣超": 3,
      "買超方向": "↑買超"
    },
    {
      "日期": "2026/07/01",
      "CB代號": "47394",
      "CB名稱": "康普四",
      "外資_買張": 0,
      "外資_賣張": 0,
      "外資_買賣超": 0,
      "投信_買張": 0,
      "投信_賣張": 0,
      "投信_買賣超": 0,
      "自營_買張": 15,
      "自營_賣張": 13,
      "自營_買賣超": 2,
      "三大法人合計買賣超": 2,
      "買超方向": "↑買超"
    },
    {
      "日期": "2026/07/01",
      "CB代號": "36804",
      "CB名稱": "家登四",
      "外資_買張": 0,
      "外資_賣張": 0,
      "外資_買賣超": 0,
      "投信_買張": 0,
      "投信_賣張": 0,
      "投信_買賣超": 0,
      "自營_買張": 123,
      "自營_賣張": 121,
      "自營_買賣超": 2,
      "三大法人合計買賣超": 2,
      "買超方向": "↑買超"
    },
    {
      "日期": "2026/07/01",
      "CB代號": "99332",
      "CB名稱": "中鼎二",
      "外資_買張": 0,
      "外資_賣張": 0,
      "外資_買賣超": 0,
      "投信_買張": 0,
      "投信_賣張": 0,
      "投信_買賣超": 0,
      "自營_買張": 2,
      "自營_賣張": 1,
      "自營_買賣超": 1,
      "三大法人合計買賣超": 1,
      "買超方向": "↑買超"
    },
    {
      "日期": "2026/07/01",
      "CB代號": "80746",
      "CB名稱": "鉅橡六",
      "外資_買張": 0,
      "外資_賣張": 0,
      "外資_買賣超": 0,
      "投信_買張": 0,
      "投信_賣張": 0,
      "投信_買賣超": 0,
      "自營_買張": 4,
      "自營_賣張": 3,
      "自營_買賣超": 1,
      "三大法人合計買賣超": 1,
      "買超方向": "↑買超"
    },
    {
      "日期": "2026/07/01",
      "CB代號": "80212",
      "CB名稱": "尖點二",
      "外資_買張": 0,
      "外資_賣張": 0,
      "外資_買賣超": 0,
      "投信_買張": 0,
      "投信_賣張": 0,
      "投信_買賣超": 0,
      "自營_買張": 12,
      "自營_賣張": 11,
      "自營_買賣超": 1,
      "三大法人合計買賣超": 1,
      "買超方向": "↑買超"
    },
    {
      "日期": "2026/07/01",
      "CB代號": "67681",
      "CB名稱": "志強一KY",
      "外資_買張": 0,
      "外資_賣張": 0,
      "外資_買賣超": 0,
      "投信_買張": 0,
      "投信_賣張": 0,
      "投信_買賣超": 0,
      "自營_買張": 4,
      "自營_賣張": 3,
      "自營_買賣超": 1,
      "三大法人合計買賣超": 1,
      "買超方向": "↑買超"
    },
    {
      "日期": "2026/07/01",
      "CB代號": "64512",
      "CB名稱": "訊芯二KY",
      "外資_買張": 0,
      "外資_賣張": 0,
      "外資_買賣超": 0,
      "投信_買張": 0,
      "投信_賣張": 0,
      "投信_買賣超": 0,
      "自營_買張": 1,
      "自營_賣張": 0,
      "自營_買賣超": 1,
      "三大法人合計買賣超": 1,
      "買超方向": "↑買超"
    },
    {
      "日期": "2026/07/01",
      "CB代號": "64324",
      "CB名稱": "今展科四",
      "外資_買張": 0,
      "外資_賣張": 0,
      "外資_買賣超": 0,
      "投信_買張": 0,
      "投信_賣張": 0,
      "投信_買賣超": 0,
      "自營_買張": 1,
      "自營_賣張": 0,
      "自營_買賣超": 1,
      "三大法人合計買賣超": 1,
      "買超方向": "↑買超"
    },
    {
      "日期": "2026/07/01",
      "CB代號": "41238",
      "CB名稱": "晟德八",
      "外資_買張": 0,
      "外資_賣張": 0,
      "外資_買賣超": 0,
      "投信_買張": 0,
      "投信_賣張": 0,
      "投信_買賣超": 0,
      "自營_買張": 9,
      "自營_賣張": 8,
      "自營_買賣超": 1,
      "三大法人合計買賣超": 1,
      "買超方向": "↑買超"
    },
    {
      "日期": "2026/07/01",
      "CB代號": "35431",
      "CB名稱": "州巧一",
      "外資_買張": 0,
      "外資_賣張": 0,
      "外資_買賣超": 0,
      "投信_買張": 0,
      "投信_賣張": 0,
      "投信_買賣超": 0,
      "自營_買張": 1,
      "自營_賣張": 0,
      "自營_買賣超": 1,
      "三大法人合計買賣超": 1,
      "買超方向": "↑買超"
    },
    {
      "日期": "2026/07/01",
      "CB代號": "35161",
      "CB名稱": "亞帝歐一",
      "外資_買張": 0,
      "外資_賣張": 0,
      "外資_買賣超": 0,
      "投信_買張": 0,
      "投信_賣張": 0,
      "投信_買賣超": 0,
      "自營_買張": 3,
      "自營_賣張": 2,
      "自營_買賣超": 1,
      "三大法人合計買賣超": 1,
      "買超方向": "↑買超"
    },
    {
      "日期": "2026/07/01",
      "CB代號": "34843",
      "CB名稱": "崧騰三",
      "外資_買張": 0,
      "外資_賣張": 0,
      "外資_買賣超": 0,
      "投信_買張": 0,
      "投信_賣張": 0,
      "投信_買賣超": 0,
      "自營_買張": 1,
      "自營_賣張": 0,
      "自營_買賣超": 1,
      "三大法人合計買賣超": 1,
      "買超方向": "↑買超"
    },
    {
      "日期": "2026/07/01",
      "CB代號": "34834",
      "CB名稱": "力致四",
      "外資_買張": 0,
      "外資_賣張": 0,
      "外資_買賣超": 0,
      "投信_買張": 0,
      "投信_賣張": 0,
      "投信_買賣超": 0,
      "自營_買張": 2,
      "自營_賣張": 1,
      "自營_買賣超": 1,
      "三大法人合計買賣超": 1,
      "買超方向": "↑買超"
    },
    {
      "日期": "2026/07/01",
      "CB代號": "33245",
      "CB名稱": "雙鴻五",
      "外資_買張": 0,
      "外資_賣張": 0,
      "外資_買賣超": 0,
      "投信_買張": 0,
      "投信_賣張": 0,
      "投信_買賣超": 0,
      "自營_買張": 9,
      "自營_賣張": 8,
      "自營_買賣超": 1,
      "三大法人合計買賣超": 1,
      "買超方向": "↑買超"
    },
    {
      "日期": "2026/07/01",
      "CB代號": "15601",
      "CB名稱": "中砂一",
      "外資_買張": 0,
      "外資_賣張": 0,
      "外資_買賣超": 0,
      "投信_買張": 0,
      "投信_賣張": 2,
      "投信_買賣超": -2,
      "自營_買張": 11,
      "自營_賣張": 8,
      "自營_買賣超": 3,
      "三大法人合計買賣超": 1,
      "買超方向": "↑買超"
    },
    {
      "日期": "2026/07/01",
      "CB代號": "15142",
      "CB名稱": "亞力二",
      "外資_買張": 0,
      "外資_賣張": 0,
      "外資_買賣超": 0,
      "投信_買張": 0,
      "投信_賣張": 8,
      "投信_買賣超": -8,
      "自營_買張": 12,
      "自營_賣張": 3,
      "自營_買賣超": 9,
      "三大法人合計買賣超": 1,
      "買超方向": "↑買超"
    },
    {
      "日期": "2026/07/01",
      "CB代號": "84624",
      "CB名稱": "柏文四",
      "外資_買張": 0,
      "外資_賣張": 0,
      "外資_買賣超": 0,
      "投信_買張": 0,
      "投信_賣張": 0,
      "投信_買賣超": 0,
      "自營_買張": 10,
      "自營_賣張": 10,
      "自營_買賣超": 0,
      "三大法人合計買賣超": 0,
      "買超方向": "持平"
    },
    {
      "日期": "2026/07/01",
      "CB代號": "84113",
      "CB名稱": "福貞三KY",
      "外資_買張": 0,
      "外資_賣張": 0,
      "外資_買賣超": 0,
      "投信_買張": 0,
      "投信_賣張": 0,
      "投信_買賣超": 0,
      "自營_買張": 41,
      "自營_賣張": 41,
      "自營_買賣超": 0,
      "三大法人合計買賣超": 0,
      "買超方向": "持平"
    },
    {
      "日期": "2026/07/01",
      "CB代號": "84041",
      "CB名稱": "百和興業一KY",
      "外資_買張": 0,
      "外資_賣張": 0,
      "外資_買賣超": 0,
      "投信_買張": 0,
      "投信_賣張": 2,
      "投信_買賣超": -2,
      "自營_買張": 2,
      "自營_賣張": 0,
      "自營_買賣超": 2,
      "三大法人合計買賣超": 0,
      "買超方向": "持平"
    },
    {
      "日期": "2026/07/01",
      "CB代號": "82551",
      "CB名稱": "朋程一",
      "外資_買張": 0,
      "外資_賣張": 0,
      "外資_買賣超": 0,
      "投信_買張": 0,
      "投信_賣張": 0,
      "投信_買賣超": 0,
      "自營_買張": 7,
      "自營_賣張": 7,
      "自營_買賣超": 0,
      "三大法人合計買賣超": 0,
      "買超方向": "持平"
    },
    {
      "日期": "2026/07/01",
      "CB代號": "82102",
      "CB名稱": "勤誠二",
      "外資_買張": 0,
      "外資_賣張": 0,
      "外資_買賣超": 0,
      "投信_買張": 0,
      "投信_賣張": 4,
      "投信_買賣超": -4,
      "自營_買張": 24,
      "自營_賣張": 20,
      "自營_買賣超": 4,
      "三大法人合計買賣超": 0,
      "買超方向": "持平"
    },
    {
      "日期": "2026/07/01",
      "CB代號": "81114",
      "CB名稱": "立碁四",
      "外資_買張": 0,
      "外資_賣張": 0,
      "外資_買賣超": 0,
      "投信_買張": 0,
      "投信_賣張": 0,
      "投信_買賣超": 0,
      "自營_買張": 1,
      "自營_賣張": 1,
      "自營_買賣超": 0,
      "三大法人合計買賣超": 0,
      "買超方向": "持平"
    },
    {
      "日期": "2026/07/01",
      "CB代號": "66702",
      "CB名稱": "復盛應用二",
      "外資_買張": 0,
      "外資_賣張": 0,
      "外資_買賣超": 0,
      "投信_買張": 0,
      "投信_賣張": 0,
      "投信_買賣超": 0,
      "自營_買張": 7,
      "自營_賣張": 7,
      "自營_買賣超": 0,
      "三大法人合計買賣超": 0,
      "買超方向": "持平"
    },
    {
      "日期": "2026/07/01",
      "CB代號": "65521",
      "CB名稱": "易華電一",
      "外資_買張": 0,
      "外資_賣張": 0,
      "外資_買賣超": 0,
      "投信_買張": 0,
      "投信_賣張": 0,
      "投信_買賣超": 0,
      "自營_買張": 2,
      "自營_賣張": 2,
      "自營_買賣超": 0,
      "三大法人合計買賣超": 0,
      "買超方向": "持平"
    },
    {
      "日期": "2026/07/01",
      "CB代號": "62075",
      "CB名稱": "雷科五",
      "外資_買張": 0,
      "外資_賣張": 0,
      "外資_買賣超": 0,
      "投信_買張": 0,
      "投信_賣張": 0,
      "投信_買賣超": 0,
      "自營_買張": 6,
      "自營_賣張": 6,
      "自營_買賣超": 0,
      "三大法人合計買賣超": 0,
      "買超方向": "持平"
    },
    {
      "日期": "2026/07/01",
      "CB代號": "61894",
      "CB名稱": "豐藝四",
      "外資_買張": 0,
      "外資_賣張": 0,
      "外資_買賣超": 0,
      "投信_買張": 0,
      "投信_賣張": 0,
      "投信_買賣超": 0,
      "自營_買張": 1,
      "自營_賣張": 1,
      "自營_買賣超": 0,
      "三大法人合計買賣超": 0,
      "買超方向": "持平"
    },
    {
      "日期": "2026/07/01",
      "CB代號": "61041",
      "CB名稱": "創惟一",
      "外資_買張": 0,
      "外資_賣張": 0,
      "外資_買賣超": 0,
      "投信_買張": 0,
      "投信_賣張": 0,
      "投信_買賣超": 0,
      "自營_買張": 3,
      "自營_賣張": 3,
      "自營_買賣超": 0,
      "三大法人合計買賣超": 0,
      "買超方向": "持平"
    },
    {
      "日期": "2026/07/01",
      "CB代號": "49311",
      "CB名稱": "新盛力一",
      "外資_買張": 0,
      "外資_賣張": 0,
      "外資_買賣超": 0,
      "投信_買張": 0,
      "投信_賣張": 0,
      "投信_買賣超": 0,
      "自營_買張": 450,
      "自營_賣張": 450,
      "自營_買賣超": 0,
      "三大法人合計買賣超": 0,
      "買超方向": "持平"
    },
    {
      "日期": "2026/07/01",
      "CB代號": "47223",
      "CB名稱": "國精化三",
      "外資_買張": 0,
      "外資_賣張": 0,
      "外資_買賣超": 0,
      "投信_買張": 0,
      "投信_賣張": 0,
      "投信_買賣超": 0,
      "自營_買張": 8,
      "自營_賣張": 8,
      "自營_買賣超": 0,
      "三大法人合計買賣超": 0,
      "買超方向": "持平"
    },
    {
      "日期": "2026/07/01",
      "CB代號": "47148",
      "CB名稱": "永捷八",
      "外資_買張": 0,
      "外資_賣張": 0,
      "外資_買賣超": 0,
      "投信_買張": 0,
      "投信_賣張": 0,
      "投信_買賣超": 0,
      "自營_買張": 1,
      "自營_賣張": 1,
      "自營_買賣超": 0,
      "三大法人合計買賣超": 0,
      "買超方向": "持平"
    },
    {
      "日期": "2026/07/01",
      "CB代號": "35513",
      "CB名稱": "世禾三",
      "外資_買張": 0,
      "外資_賣張": 0,
      "外資_買賣超": 0,
      "投信_買張": 0,
      "投信_賣張": 0,
      "投信_買賣超": 0,
      "自營_買張": 2,
      "自營_賣張": 2,
      "自營_買賣超": 0,
      "三大法人合計買賣超": 0,
      "買超方向": "持平"
    },
    {
      "日期": "2026/07/01",
      "CB代號": "35266",
      "CB名稱": "凡甲六",
      "外資_買張": 0,
      "外資_賣張": 0,
      "外資_買賣超": 0,
      "投信_買張": 0,
      "投信_賣張": 0,
      "投信_買賣超": 0,
      "自營_買張": 9,
      "自營_賣張": 9,
      "自營_買賣超": 0,
      "三大法人合計買賣超": 0,
      "買超方向": "持平"
    },
    {
      "日期": "2026/07/01",
      "CB代號": "35181",
      "CB名稱": "柏騰一",
      "外資_買張": 0,
      "外資_賣張": 0,
      "外資_買賣超": 0,
      "投信_買張": 0,
      "投信_賣張": 0,
      "投信_買賣超": 0,
      "自營_買張": 1,
      "自營_賣張": 1,
      "自營_買賣超": 0,
      "三大法人合計買賣超": 0,
      "買超方向": "持平"
    },
    {
      "日期": "2026/07/01",
      "CB代號": "33902",
      "CB名稱": "旭軟二",
      "外資_買張": 0,
      "外資_賣張": 0,
      "外資_買賣超": 0,
      "投信_買張": 0,
      "投信_賣張": 0,
      "投信_買賣超": 0,
      "自營_買張": 4,
      "自營_賣張": 4,
      "自營_買賣超": 0,
      "三大法人合計買賣超": 0,
      "買超方向": "持平"
    },
    {
      "日期": "2026/07/01",
      "CB代號": "31413",
      "CB名稱": "晶宏三",
      "外資_買張": 0,
      "外資_賣張": 0,
      "外資_買賣超": 0,
      "投信_買張": 0,
      "投信_賣張": 0,
      "投信_買賣超": 0,
      "自營_買張": 5,
      "自營_賣張": 5,
      "自營_買賣超": 0,
      "三大法人合計買賣超": 0,
      "買超方向": "持平"
    },
    {
      "日期": "2026/07/01",
      "CB代號": "30321",
      "CB名稱": "偉訓一",
      "外資_買張": 0,
      "外資_賣張": 0,
      "外資_買賣超": 0,
      "投信_買張": 0,
      "投信_賣張": 0,
      "投信_買賣超": 0,
      "自營_買張": 5,
      "自營_賣張": 5,
      "自營_買賣超": 0,
      "三大法人合計買賣超": 0,
      "買超方向": "持平"
    },
    {
      "日期": "2026/07/01",
      "CB代號": "30134",
      "CB名稱": "晟銘電四",
      "外資_買張": 0,
      "外資_賣張": 0,
      "外資_買賣超": 0,
      "投信_買張": 0,
      "投信_賣張": 0,
      "投信_買賣超": 0,
      "自營_買張": 1,
      "自營_賣張": 1,
      "自營_買賣超": 0,
      "三大法人合計買賣超": 0,
      "買超方向": "持平"
    },
    {
      "日期": "2026/07/01",
      "CB代號": "29061",
      "CB名稱": "高林一",
      "外資_買張": 0,
      "外資_賣張": 0,
      "外資_買賣超": 0,
      "投信_買張": 0,
      "投信_賣張": 0,
      "投信_買賣超": 0,
      "自營_買張": 5,
      "自營_賣張": 5,
      "自營_買賣超": 0,
      "三大法人合計買賣超": 0,
      "買超方向": "持平"
    },
    {
      "日期": "2026/07/01",
      "CB代號": "27532",
      "CB名稱": "八方雲集二",
      "外資_買張": 0,
      "外資_賣張": 0,
      "外資_買賣超": 0,
      "投信_買張": 0,
      "投信_賣張": 0,
      "投信_買賣超": 0,
      "自營_買張": 1,
      "自營_賣張": 1,
      "自營_買賣超": 0,
      "三大法人合計買賣超": 0,
      "買超方向": "持平"
    },
    {
      "日期": "2026/07/01",
      "CB代號": "27531",
      "CB名稱": "八方雲集一",
      "外資_買張": 0,
      "外資_賣張": 0,
      "外資_買賣超": 0,
      "投信_買張": 0,
      "投信_賣張": 0,
      "投信_買賣超": 0,
      "自營_買張": 2,
      "自營_賣張": 2,
      "自營_買賣超": 0,
      "三大法人合計買賣超": 0,
      "買超方向": "持平"
    },
    {
      "日期": "2026/07/01",
      "CB代號": "24866",
      "CB名稱": "一詮六",
      "外資_買張": 0,
      "外資_賣張": 0,
      "外資_買賣超": 0,
      "投信_買張": 0,
      "投信_賣張": 0,
      "投信_買賣超": 0,
      "自營_買張": 10,
      "自營_賣張": 10,
      "自營_買賣超": 0,
      "三大法人合計買賣超": 0,
      "買超方向": "持平"
    },
    {
      "日期": "2026/07/01",
      "CB代號": "24762",
      "CB名稱": "鉅祥二",
      "外資_買張": 0,
      "外資_賣張": 0,
      "外資_買賣超": 0,
      "投信_買張": 0,
      "投信_賣張": 0,
      "投信_買賣超": 0,
      "自營_買張": 4,
      "自營_賣張": 4,
      "自營_買賣超": 0,
      "三大法人合計買賣超": 0,
      "買超方向": "持平"
    },
    {
      "日期": "2026/07/01",
      "CB代號": "24553",
      "CB名稱": "全新三",
      "外資_買張": 0,
      "外資_賣張": 0,
      "外資_買賣超": 0,
      "投信_買張": 0,
      "投信_賣張": 0,
      "投信_買賣超": 0,
      "自營_買張": 6,
      "自營_賣張": 6,
      "自營_買賣超": 0,
      "三大法人合計買賣超": 0,
      "買超方向": "持平"
    },
    {
      "日期": "2026/07/01",
      "CB代號": "24394",
      "CB名稱": "美律四",
      "外資_買張": 0,
      "外資_賣張": 0,
      "外資_買賣超": 0,
      "投信_買張": 0,
      "投信_賣張": 0,
      "投信_買賣超": 0,
      "自營_買張": 1,
      "自營_賣張": 1,
      "自營_買賣超": 0,
      "三大法人合計買賣超": 0,
      "買超方向": "持平"
    },
    {
      "日期": "2026/07/01",
      "CB代號": "22471",
      "CB名稱": "汎德永業一",
      "外資_買張": 0,
      "外資_賣張": 0,
      "外資_買賣超": 0,
      "投信_買張": 0,
      "投信_賣張": 0,
      "投信_買賣超": 0,
      "自營_買張": 24,
      "自營_賣張": 24,
      "自營_買賣超": 0,
      "三大法人合計買賣超": 0,
      "買超方向": "持平"
    },
    {
      "日期": "2026/07/01",
      "CB代號": "84762",
      "CB名稱": "台境二",
      "外資_買張": 0,
      "外資_賣張": 0,
      "外資_買賣超": 0,
      "投信_買張": 0,
      "投信_賣張": 0,
      "投信_買賣超": 0,
      "自營_買張": 0,
      "自營_賣張": 1,
      "自營_買賣超": -1,
      "三大法人合計買賣超": -1,
      "買超方向": "↓賣超"
    },
    {
      "日期": "2026/07/01",
      "CB代號": "811210",
      "CB名稱": "至上十",
      "外資_買張": 0,
      "外資_賣張": 0,
      "外資_買賣超": 0,
      "投信_買張": 0,
      "投信_賣張": 0,
      "投信_買賣超": 0,
      "自營_買張": 70,
      "自營_賣張": 71,
      "自營_買賣超": -1,
      "三大法人合計買賣超": -1,
      "買超方向": "↓賣超"
    },
    {
      "日期": "2026/07/01",
      "CB代號": "66642",
      "CB名稱": "群翊二",
      "外資_買張": 0,
      "外資_賣張": 0,
      "外資_買賣超": 0,
      "投信_買張": 0,
      "投信_賣張": 0,
      "投信_買賣超": 0,
      "自營_買張": 17,
      "自營_賣張": 18,
      "自營_買賣超": -1,
      "三大法人合計買賣超": -1,
      "買超方向": "↓賣超"
    },
    {
      "日期": "2026/07/01",
      "CB代號": "62843",
      "CB名稱": "佳邦三",
      "外資_買張": 0,
      "外資_賣張": 0,
      "外資_買賣超": 0,
      "投信_買張": 0,
      "投信_賣張": 0,
      "投信_買賣超": 0,
      "自營_買張": 40,
      "自營_賣張": 41,
      "自營_買賣超": -1,
      "三大法人合計買賣超": -1,
      "買超方向": "↓賣超"
    },
    {
      "日期": "2026/07/01",
      "CB代號": "52844",
      "CB名稱": "jpp四KY",
      "外資_買張": 0,
      "外資_賣張": 0,
      "外資_買賣超": 0,
      "投信_買張": 0,
      "投信_賣張": 0,
      "投信_買賣超": 0,
      "自營_買張": 0,
      "自營_賣張": 1,
      "自營_買賣超": -1,
      "三大法人合計買賣超": -1,
      "買超方向": "↓賣超"
    },
    {
      "日期": "2026/07/01",
      "CB代號": "52303",
      "CB名稱": "雷笛克光學三",
      "外資_買張": 0,
      "外資_賣張": 0,
      "外資_買賣超": 0,
      "投信_買張": 0,
      "投信_賣張": 0,
      "投信_買賣超": 0,
      "自營_買張": 2,
      "自營_賣張": 3,
      "自營_買賣超": -1,
      "三大法人合計買賣超": -1,
      "買超方向": "↓賣超"
    },
    {
      "日期": "2026/07/01",
      "CB代號": "45721",
      "CB名稱": "駐龍一",
      "外資_買張": 0,
      "外資_賣張": 0,
      "外資_買賣超": 0,
      "投信_買張": 0,
      "投信_賣張": 0,
      "投信_買賣超": 0,
      "自營_買張": 25,
      "自營_賣張": 26,
      "自營_買賣超": -1,
      "三大法人合計買賣超": -1,
      "買超方向": "↓賣超"
    },
    {
      "日期": "2026/07/01",
      "CB代號": "36053",
      "CB名稱": "宏致三",
      "外資_買張": 0,
      "外資_賣張": 0,
      "外資_買賣超": 0,
      "投信_買張": 0,
      "投信_賣張": 0,
      "投信_買賣超": 0,
      "自營_買張": 0,
      "自營_賣張": 1,
      "自營_買賣超": -1,
      "三大法人合計買賣超": -1,
      "買超方向": "↓賣超"
    },
    {
      "日期": "2026/07/01",
      "CB代號": "33881",
      "CB名稱": "崇越電一",
      "外資_買張": 0,
      "外資_賣張": 0,
      "外資_買賣超": 0,
      "投信_買張": 0,
      "投信_賣張": 0,
      "投信_買賣超": 0,
      "自營_買張": 2,
      "自營_賣張": 3,
      "自營_買賣超": -1,
      "三大法人合計買賣超": -1,
      "買超方向": "↓賣超"
    },
    {
      "日期": "2026/07/01",
      "CB代號": "24023",
      "CB名稱": "毅嘉三",
      "外資_買張": 0,
      "外資_賣張": 0,
      "外資_買賣超": 0,
      "投信_買張": 0,
      "投信_賣張": 0,
      "投信_買賣超": 0,
      "自營_買張": 14,
      "自營_賣張": 15,
      "自營_買賣超": -1,
      "三大法人合計買賣超": -1,
      "買超方向": "↓賣超"
    },
    {
      "日期": "2026/07/01",
      "CB代號": "16095",
      "CB名稱": "大亞五",
      "外資_買張": 0,
      "外資_賣張": 0,
      "外資_買賣超": 0,
      "投信_買張": 0,
      "投信_賣張": 0,
      "投信_買賣超": 0,
      "自營_買張": 0,
      "自營_賣張": 1,
      "自營_買賣超": -1,
      "三大法人合計買賣超": -1,
      "買超方向": "↓賣超"
    },
    {
      "日期": "2026/07/01",
      "CB代號": "14743",
      "CB名稱": "弘裕三",
      "外資_買張": 0,
      "外資_賣張": 0,
      "外資_買賣超": 0,
      "投信_買張": 0,
      "投信_賣張": 0,
      "投信_買賣超": 0,
      "自營_買張": 0,
      "自營_賣張": 1,
      "自營_買賣超": -1,
      "三大法人合計買賣超": -1,
      "買超方向": "↓賣超"
    },
    {
      "日期": "2026/07/01",
      "CB代號": "24552",
      "CB名稱": "全新二",
      "外資_買張": 0,
      "外資_賣張": 0,
      "外資_買賣超": 0,
      "投信_買張": 0,
      "投信_賣張": 0,
      "投信_買賣超": 0,
      "自營_買張": 28,
      "自營_賣張": 30,
      "自營_買賣超": -2,
      "三大法人合計買賣超": -2,
      "買超方向": "↓賣超"
    },
    {
      "日期": "2026/07/01",
      "CB代號": "82993",
      "CB名稱": "群聯三",
      "外資_買張": 0,
      "外資_賣張": 0,
      "外資_買賣超": 0,
      "投信_買張": 2,
      "投信_賣張": 0,
      "投信_買賣超": 2,
      "自營_買張": 352,
      "自營_賣張": 357,
      "自營_買賣超": -5,
      "三大法人合計買賣超": -3,
      "買超方向": "↓賣超"
    },
    {
      "日期": "2026/07/01",
      "CB代號": "81473",
      "CB名稱": "正淩三",
      "外資_買張": 0,
      "外資_賣張": 0,
      "外資_買賣超": 0,
      "投信_買張": 0,
      "投信_賣張": 0,
      "投信_買賣超": 0,
      "自營_買張": 12,
      "自營_賣張": 15,
      "自營_買賣超": -3,
      "三大法人合計買賣超": -3,
      "買超方向": "↓賣超"
    },
    {
      "日期": "2026/07/01",
      "CB代號": "68701",
      "CB名稱": "騰雲一",
      "外資_買張": 0,
      "外資_賣張": 0,
      "外資_買賣超": 0,
      "投信_買張": 0,
      "投信_賣張": 0,
      "投信_買賣超": 0,
      "自營_買張": 1,
      "自營_賣張": 4,
      "自營_買賣超": -3,
      "三大法人合計買賣超": -3,
      "買超方向": "↓賣超"
    },
    {
      "日期": "2026/07/01",
      "CB代號": "65851",
      "CB名稱": "鼎基一",
      "外資_買張": 0,
      "外資_賣張": 0,
      "外資_買賣超": 0,
      "投信_買張": 0,
      "投信_賣張": 0,
      "投信_買賣超": 0,
      "自營_買張": 1,
      "自營_賣張": 4,
      "自營_買賣超": -3,
      "三大法人合計買賣超": -3,
      "買超方向": "↓賣超"
    },
    {
      "日期": "2026/07/01",
      "CB代號": "61907",
      "CB名稱": "萬泰科七",
      "外資_買張": 0,
      "外資_賣張": 0,
      "外資_買賣超": 0,
      "投信_買張": 0,
      "投信_賣張": 0,
      "投信_買賣超": 0,
      "自營_買張": 3,
      "自營_賣張": 6,
      "自營_買賣超": -3,
      "三大法人合計買賣超": -3,
      "買超方向": "↓賣超"
    },
    {
      "日期": "2026/07/01",
      "CB代號": "41684",
      "CB名稱": "醣聯四",
      "外資_買張": 0,
      "外資_賣張": 0,
      "外資_買賣超": 0,
      "投信_買張": 0,
      "投信_賣張": 0,
      "投信_買賣超": 0,
      "自營_買張": 1,
      "自營_賣張": 4,
      "自營_買賣超": -3,
      "三大法人合計買賣超": -3,
      "買超方向": "↓賣超"
    },
    {
      "日期": "2026/07/01",
      "CB代號": "35267",
      "CB名稱": "凡甲七",
      "外資_買張": 0,
      "外資_賣張": 0,
      "外資_買賣超": 0,
      "投信_買張": 0,
      "投信_賣張": 0,
      "投信_買賣超": 0,
      "自營_買張": 15,
      "自營_賣張": 18,
      "自營_買賣超": -3,
      "三大法人合計買賣超": -3,
      "買超方向": "↓賣超"
    },
    {
      "日期": "2026/07/01",
      "CB代號": "24672",
      "CB名稱": "志聖二",
      "外資_買張": 0,
      "外資_賣張": 0,
      "外資_買賣超": 0,
      "投信_買張": 0,
      "投信_賣張": 0,
      "投信_買賣超": 0,
      "自營_買張": 10,
      "自營_賣張": 13,
      "自營_買賣超": -3,
      "三大法人合計買賣超": -3,
      "買超方向": "↓賣超"
    },
    {
      "日期": "2026/07/01",
      "CB代號": "23383",
      "CB名稱": "光罩三",
      "外資_買張": 0,
      "外資_賣張": 0,
      "外資_買賣超": 0,
      "投信_買張": 0,
      "投信_賣張": 0,
      "投信_買賣超": 0,
      "自營_買張": 0,
      "自營_賣張": 3,
      "自營_買賣超": -3,
      "三大法人合計買賣超": -3,
      "買超方向": "↓賣超"
    },
    {
      "日期": "2026/07/01",
      "CB代號": "99392",
      "CB名稱": "宏全二",
      "外資_買張": 0,
      "外資_賣張": 0,
      "外資_買賣超": 0,
      "投信_買張": 0,
      "投信_賣張": 0,
      "投信_買賣超": 0,
      "自營_買張": 59,
      "自營_賣張": 63,
      "自營_買賣超": -4,
      "三大法人合計買賣超": -4,
      "買超方向": "↓賣超"
    },
    {
      "日期": "2026/07/01",
      "CB代號": "65152",
      "CB名稱": "穎崴二",
      "外資_買張": 0,
      "外資_賣張": 0,
      "外資_買賣超": 0,
      "投信_買張": 0,
      "投信_賣張": 0,
      "投信_買賣超": 0,
      "自營_買張": 141,
      "自營_賣張": 145,
      "自營_買賣超": -4,
      "三大法人合計買賣超": -4,
      "買超方向": "↓賣超"
    },
    {
      "日期": "2026/07/01",
      "CB代號": "52635",
      "CB名稱": "智崴五",
      "外資_買張": 0,
      "外資_賣張": 0,
      "外資_買賣超": 0,
      "投信_買張": 0,
      "投信_賣張": 0,
      "投信_買賣超": 0,
      "自營_買張": 20,
      "自營_賣張": 24,
      "自營_買賣超": -4,
      "三大法人合計買賣超": -4,
      "買超方向": "↓賣超"
    },
    {
      "日期": "2026/07/01",
      "CB代號": "33763",
      "CB名稱": "新日興三",
      "外資_買張": 0,
      "外資_賣張": 0,
      "外資_買賣超": 0,
      "投信_買張": 0,
      "投信_賣張": 0,
      "投信_買賣超": 0,
      "自營_買張": 1,
      "自營_賣張": 5,
      "自營_買賣超": -4,
      "三大法人合計買賣超": -4,
      "買超方向": "↓賣超"
    },
    {
      "日期": "2026/07/01",
      "CB代號": "31352",
      "CB名稱": "凌航二",
      "外資_買張": 0,
      "外資_賣張": 0,
      "外資_買賣超": 0,
      "投信_買張": 0,
      "投信_賣張": 0,
      "投信_買賣超": 0,
      "自營_買張": 123,
      "自營_賣張": 127,
      "自營_買賣超": -4,
      "三大法人合計買賣超": -4,
      "買超方向": "↓賣超"
    },
    {
      "日期": "2026/07/01",
      "CB代號": "23511",
      "CB名稱": "順德一",
      "外資_買張": 0,
      "外資_賣張": 0,
      "外資_買賣超": 0,
      "投信_買張": 0,
      "投信_賣張": 0,
      "投信_買賣超": 0,
      "自營_買張": 27,
      "自營_賣張": 31,
      "自營_買賣超": -4,
      "三大法人合計買賣超": -4,
      "買超方向": "↓賣超"
    },
    {
      "日期": "2026/07/01",
      "CB代號": "68702",
      "CB名稱": "騰雲二",
      "外資_買張": 0,
      "外資_賣張": 0,
      "外資_買賣超": 0,
      "投信_買張": 0,
      "投信_賣張": 0,
      "投信_買賣超": 0,
      "自營_買張": 5,
      "自營_賣張": 10,
      "自營_買賣超": -5,
      "三大法人合計買賣超": -5,
      "買超方向": "↓賣超"
    },
    {
      "日期": "2026/07/01",
      "CB代號": "33621",
      "CB名稱": "先進光一",
      "外資_買張": 0,
      "外資_賣張": 0,
      "外資_買賣超": 0,
      "投信_買張": 0,
      "投信_賣張": 0,
      "投信_買賣超": 0,
      "自營_買張": 101,
      "自營_賣張": 106,
      "自營_買賣超": -5,
      "三大法人合計買賣超": -5,
      "買超方向": "↓賣超"
    },
    {
      "日期": "2026/07/01",
      "CB代號": "30337",
      "CB名稱": "威健七",
      "外資_買張": 0,
      "外資_賣張": 0,
      "外資_買賣超": 0,
      "投信_買張": 0,
      "投信_賣張": 0,
      "投信_買賣超": 0,
      "自營_買張": 22,
      "自營_賣張": 27,
      "自營_買賣超": -5,
      "三大法人合計買賣超": -5,
      "買超方向": "↓賣超"
    },
    {
      "日期": "2026/07/01",
      "CB代號": "15364",
      "CB名稱": "和大四",
      "外資_買張": 0,
      "外資_賣張": 0,
      "外資_買賣超": 0,
      "投信_買張": 0,
      "投信_賣張": 0,
      "投信_買賣超": 0,
      "自營_買張": 0,
      "自營_賣張": 5,
      "自營_買賣超": -5,
      "三大法人合計買賣超": -5,
      "買超方向": "↓賣超"
    },
    {
      "日期": "2026/07/01",
      "CB代號": "36872",
      "CB名稱": "歐買尬二",
      "外資_買張": 0,
      "外資_賣張": 0,
      "外資_買賣超": 0,
      "投信_買張": 0,
      "投信_賣張": 0,
      "投信_買賣超": 0,
      "自營_買張": 4,
      "自營_賣張": 10,
      "自營_買賣超": -6,
      "三大法人合計買賣超": -6,
      "買超方向": "↓賣超"
    },
    {
      "日期": "2026/07/01",
      "CB代號": "30322",
      "CB名稱": "偉訓二",
      "外資_買張": 0,
      "外資_賣張": 0,
      "外資_買賣超": 0,
      "投信_買張": 0,
      "投信_賣張": 0,
      "投信_買賣超": 0,
      "自營_買張": 10,
      "自營_賣張": 16,
      "自營_買賣超": -6,
      "三大法人合計買賣超": -6,
      "買超方向": "↓賣超"
    },
    {
      "日期": "2026/07/01",
      "CB代號": "80914",
      "CB名稱": "翔名四",
      "外資_買張": 0,
      "外資_賣張": 0,
      "外資_買賣超": 0,
      "投信_買張": 0,
      "投信_賣張": 0,
      "投信_買賣超": 0,
      "自營_買張": 5,
      "自營_賣張": 12,
      "自營_買賣超": -7,
      "三大法人合計買賣超": -7,
      "買超方向": "↓賣超"
    },
    {
      "日期": "2026/07/01",
      "CB代號": "61011",
      "CB名稱": "寬魚國際一",
      "外資_買張": 0,
      "外資_賣張": 0,
      "外資_買賣超": 0,
      "投信_買張": 0,
      "投信_賣張": 0,
      "投信_買賣超": 0,
      "自營_買張": 12,
      "自營_賣張": 19,
      "自營_買賣超": -7,
      "三大法人合計買賣超": -7,
      "買超方向": "↓賣超"
    },
    {
      "日期": "2026/07/01",
      "CB代號": "34793",
      "CB名稱": "安勤三",
      "外資_買張": 0,
      "外資_賣張": 0,
      "外資_買賣超": 0,
      "投信_買張": 0,
      "投信_賣張": 0,
      "投信_買賣超": 0,
      "自營_買張": 16,
      "自營_賣張": 23,
      "自營_買賣超": -7,
      "三大法人合計買賣超": -7,
      "買超方向": "↓賣超"
    },
    {
      "日期": "2026/07/01",
      "CB代號": "65852",
      "CB名稱": "鼎基二",
      "外資_買張": 0,
      "外資_賣張": 0,
      "外資_買賣超": 0,
      "投信_買張": 0,
      "投信_賣張": 0,
      "投信_買賣超": 0,
      "自營_買張": 0,
      "自營_賣張": 8,
      "自營_買賣超": -8,
      "三大法人合計買賣超": -8,
      "買超方向": "↓賣超"
    },
    {
      "日期": "2026/07/01",
      "CB代號": "61973",
      "CB名稱": "佳必琪三",
      "外資_買張": 18,
      "外資_賣張": 0,
      "外資_買賣超": 18,
      "投信_買張": 0,
      "投信_賣張": 0,
      "投信_買賣超": 0,
      "自營_買張": 14,
      "自營_賣張": 40,
      "自營_買賣超": -26,
      "三大法人合計買賣超": -8,
      "買超方向": "↓賣超"
    },
    {
      "日期": "2026/07/01",
      "CB代號": "49674",
      "CB名稱": "十銓四",
      "外資_買張": 0,
      "外資_賣張": 0,
      "外資_買賣超": 0,
      "投信_買張": 0,
      "投信_賣張": 0,
      "投信_買賣超": 0,
      "自營_買張": 32,
      "自營_賣張": 41,
      "自營_買賣超": -9,
      "三大法人合計買賣超": -9,
      "買超方向": "↓賣超"
    },
    {
      "日期": "2026/07/01",
      "CB代號": "30112",
      "CB名稱": "今皓二",
      "外資_買張": 0,
      "外資_賣張": 0,
      "外資_買賣超": 0,
      "投信_買張": 0,
      "投信_賣張": 0,
      "投信_買賣超": 0,
      "自營_買張": 14,
      "自營_賣張": 23,
      "自營_買賣超": -9,
      "三大法人合計買賣超": -9,
      "買超方向": "↓賣超"
    },
    {
      "日期": "2026/07/01",
      "CB代號": "54642",
      "CB名稱": "霖宏二",
      "外資_買張": 0,
      "外資_賣張": 0,
      "外資_買賣超": 0,
      "投信_買張": 0,
      "投信_賣張": 0,
      "投信_買賣超": 0,
      "自營_買張": 0,
      "自營_賣張": 10,
      "自營_買賣超": -10,
      "三大法人合計買賣超": -10,
      "買超方向": "↓賣超"
    },
    {
      "日期": "2026/07/01",
      "CB代號": "33571",
      "CB名稱": "臺慶科一",
      "外資_買張": 0,
      "外資_賣張": 0,
      "外資_買賣超": 0,
      "投信_買張": 0,
      "投信_賣張": 0,
      "投信_買賣超": 0,
      "自營_買張": 0,
      "自營_賣張": 10,
      "自營_買賣超": -10,
      "三大法人合計買賣超": -10,
      "買超方向": "↓賣超"
    },
    {
      "日期": "2026/07/01",
      "CB代號": "13382",
      "CB名稱": "廣華二KY",
      "外資_買張": 0,
      "外資_賣張": 0,
      "外資_買賣超": 0,
      "投信_買張": 0,
      "投信_賣張": 0,
      "投信_買賣超": 0,
      "自營_買張": 0,
      "自營_賣張": 10,
      "自營_買賣超": -10,
      "三大法人合計買賣超": -10,
      "買超方向": "↓賣超"
    },
    {
      "日期": "2026/07/01",
      "CB代號": "68351",
      "CB名稱": "圓裕一",
      "外資_買張": 0,
      "外資_賣張": 0,
      "外資_買賣超": 0,
      "投信_買張": 0,
      "投信_賣張": 0,
      "投信_買賣超": 0,
      "自營_買張": 0,
      "自營_賣張": 11,
      "自營_買賣超": -11,
      "三大法人合計買賣超": -11,
      "買超方向": "↓賣超"
    },
    {
      "日期": "2026/07/01",
      "CB代號": "34163",
      "CB名稱": "融程電三",
      "外資_買張": 0,
      "外資_賣張": 0,
      "外資_買賣超": 0,
      "投信_買張": 0,
      "投信_賣張": 0,
      "投信_買賣超": 0,
      "自營_買張": 2,
      "自營_賣張": 14,
      "自營_買賣超": -12,
      "三大法人合計買賣超": -12,
      "買超方向": "↓賣超"
    },
    {
      "日期": "2026/07/01",
      "CB代號": "53887",
      "CB名稱": "中磊七",
      "外資_買張": 0,
      "外資_賣張": 0,
      "外資_買賣超": 0,
      "投信_買張": 0,
      "投信_賣張": 0,
      "投信_買賣超": 0,
      "自營_買張": 39,
      "自營_賣張": 54,
      "自營_買賣超": -15,
      "三大法人合計買賣超": -15,
      "買超方向": "↓賣超"
    },
    {
      "日期": "2026/07/01",
      "CB代號": "32571",
      "CB名稱": "虹冠電一",
      "外資_買張": 0,
      "外資_賣張": 0,
      "外資_買賣超": 0,
      "投信_買張": 0,
      "投信_賣張": 0,
      "投信_買賣超": 0,
      "自營_買張": 0,
      "自營_賣張": 15,
      "自營_買賣超": -15,
      "三大法人合計買賣超": -15,
      "買超方向": "↓賣超"
    },
    {
      "日期": "2026/07/01",
      "CB代號": "27551",
      "CB名稱": "揚秦一",
      "外資_買張": 0,
      "外資_賣張": 0,
      "外資_買賣超": 0,
      "投信_買張": 0,
      "投信_賣張": 0,
      "投信_買賣超": 0,
      "自營_買張": 0,
      "自營_賣張": 15,
      "自營_買賣超": -15,
      "三大法人合計買賣超": -15,
      "買超方向": "↓賣超"
    },
    {
      "日期": "2026/07/01",
      "CB代號": "47491",
      "CB名稱": "新應材一",
      "外資_買張": 0,
      "外資_賣張": 0,
      "外資_買賣超": 0,
      "投信_買張": 20,
      "投信_賣張": 0,
      "投信_買賣超": 20,
      "自營_買張": 26,
      "自營_賣張": 62,
      "自營_買賣超": -36,
      "三大法人合計買賣超": -16,
      "買超方向": "↓賣超"
    },
    {
      "日期": "2026/07/01",
      "CB代號": "36913",
      "CB名稱": "碩禾三",
      "外資_買張": 0,
      "外資_賣張": 0,
      "外資_買賣超": 0,
      "投信_買張": 0,
      "投信_賣張": 0,
      "投信_買賣超": 0,
      "自營_買張": 28,
      "自營_賣張": 46,
      "自營_買賣超": -18,
      "三大法人合計買賣超": -18,
      "買超方向": "↓賣超"
    },
    {
      "日期": "2026/07/01",
      "CB代號": "69571",
      "CB名稱": "裕慶一KY",
      "外資_買張": 0,
      "外資_賣張": 0,
      "外資_買賣超": 0,
      "投信_買張": 0,
      "投信_賣張": 0,
      "投信_買賣超": 0,
      "自營_買張": 0,
      "自營_賣張": 20,
      "自營_買賣超": -20,
      "三大法人合計買賣超": -20,
      "買超方向": "↓賣超"
    },
    {
      "日期": "2026/07/01",
      "CB代號": "68301",
      "CB名稱": "汎銓一",
      "外資_買張": 0,
      "外資_賣張": 0,
      "外資_買賣超": 0,
      "投信_買張": 0,
      "投信_賣張": 0,
      "投信_買賣超": 0,
      "自營_買張": 14,
      "自營_賣張": 35,
      "自營_買賣超": -21,
      "三大法人合計買賣超": -21,
      "買超方向": "↓賣超"
    },
    {
      "日期": "2026/07/01",
      "CB代號": "31311",
      "CB名稱": "弘塑一",
      "外資_買張": 0,
      "外資_賣張": 0,
      "外資_買賣超": 0,
      "投信_買張": 0,
      "投信_賣張": 0,
      "投信_買賣超": 0,
      "自營_買張": 45,
      "自營_賣張": 68,
      "自營_買賣超": -23,
      "三大法人合計買賣超": -23,
      "買超方向": "↓賣超"
    },
    {
      "日期": "2026/07/01",
      "CB代號": "53096",
      "CB名稱": "系統電六",
      "外資_買張": 0,
      "外資_賣張": 0,
      "外資_買賣超": 0,
      "投信_買張": 0,
      "投信_賣張": 0,
      "投信_買賣超": 0,
      "自營_買張": 5,
      "自營_賣張": 30,
      "自營_買賣超": -25,
      "三大法人合計買賣超": -25,
      "買超方向": "↓賣超"
    },
    {
      "日期": "2026/07/01",
      "CB代號": "65331",
      "CB名稱": "晶心科一",
      "外資_買張": 0,
      "外資_賣張": 0,
      "外資_買賣超": 0,
      "投信_買張": 0,
      "投信_賣張": 0,
      "投信_買賣超": 0,
      "自營_買張": 20,
      "自營_賣張": 46,
      "自營_買賣超": -26,
      "三大法人合計買賣超": -26,
      "買超方向": "↓賣超"
    },
    {
      "日期": "2026/07/01",
      "CB代號": "61565",
      "CB名稱": "松上五",
      "外資_買張": 0,
      "外資_賣張": 0,
      "外資_買賣超": 0,
      "投信_買張": 0,
      "投信_賣張": 0,
      "投信_買賣超": 0,
      "自營_買張": 41,
      "自營_賣張": 68,
      "自營_買賣超": -27,
      "三大法人合計買賣超": -27,
      "買超方向": "↓賣超"
    },
    {
      "日期": "2026/07/01",
      "CB代號": "65381",
      "CB名稱": "倉和一",
      "外資_買張": 0,
      "外資_賣張": 0,
      "外資_買賣超": 0,
      "投信_買張": 0,
      "投信_賣張": 0,
      "投信_買賣超": 0,
      "自營_買張": 21,
      "自營_賣張": 51,
      "自營_買賣超": -30,
      "三大法人合計買賣超": -30,
      "買超方向": "↓賣超"
    },
    {
      "日期": "2026/07/01",
      "CB代號": "35831",
      "CB名稱": "辛耘一",
      "外資_買張": 0,
      "外資_賣張": 0,
      "外資_買賣超": 0,
      "投信_買張": 0,
      "投信_賣張": 0,
      "投信_買賣超": 0,
      "自營_買張": 41,
      "自營_賣張": 72,
      "自營_買賣超": -31,
      "三大法人合計買賣超": -31,
      "買超方向": "↓賣超"
    },
    {
      "日期": "2026/07/01",
      "CB代號": "14363",
      "CB名稱": "華友聯三",
      "外資_買張": 0,
      "外資_賣張": 0,
      "外資_買賣超": 0,
      "投信_買張": 0,
      "投信_賣張": 0,
      "投信_買賣超": 0,
      "自營_買張": 0,
      "自營_賣張": 35,
      "自營_買賣超": -35,
      "三大法人合計買賣超": -35,
      "買超方向": "↓賣超"
    },
    {
      "日期": "2026/07/01",
      "CB代號": "61827",
      "CB名稱": "合晶七",
      "外資_買張": 0,
      "外資_賣張": 0,
      "外資_買賣超": 0,
      "投信_買張": 0,
      "投信_賣張": 0,
      "投信_買賣超": 0,
      "自營_買張": 23,
      "自營_賣張": 61,
      "自營_買賣超": -38,
      "三大法人合計買賣超": -38,
      "買超方向": "↓賣超"
    },
    {
      "日期": "2026/07/01",
      "CB代號": "370201",
      "CB名稱": "大聯大E1",
      "外資_買張": 0,
      "外資_賣張": 0,
      "外資_買賣超": 0,
      "投信_買張": 0,
      "投信_賣張": 0,
      "投信_買賣超": 0,
      "自營_買張": 27,
      "自營_賣張": 65,
      "自營_買賣超": -38,
      "三大法人合計買賣超": -38,
      "買超方向": "↓賣超"
    },
    {
      "日期": "2026/07/01",
      "CB代號": "68032",
      "CB名稱": "崑鼎二",
      "外資_買張": 0,
      "外資_賣張": 0,
      "外資_買賣超": 0,
      "投信_買張": 0,
      "投信_賣張": 0,
      "投信_買賣超": 0,
      "自營_買張": 0,
      "自營_賣張": 41,
      "自營_買賣超": -41,
      "三大法人合計買賣超": -41,
      "買超方向": "↓賣超"
    },
    {
      "日期": "2026/07/01",
      "CB代號": "30455",
      "CB名稱": "台灣大五",
      "外資_買張": 0,
      "外資_賣張": 0,
      "外資_買賣超": 0,
      "投信_買張": 0,
      "投信_賣張": 0,
      "投信_買賣超": 0,
      "自營_買張": 18,
      "自營_賣張": 59,
      "自營_買賣超": -41,
      "三大法人合計買賣超": -41,
      "買超方向": "↓賣超"
    },
    {
      "日期": "2026/07/01",
      "CB代號": "61828",
      "CB名稱": "合晶八",
      "外資_買張": 0,
      "外資_賣張": 0,
      "外資_買賣超": 0,
      "投信_買張": 0,
      "投信_賣張": 0,
      "投信_買賣超": 0,
      "自營_買張": 3,
      "自營_賣張": 45,
      "自營_買賣超": -42,
      "三大法人合計買賣超": -42,
      "買超方向": "↓賣超"
    },
    {
      "日期": "2026/07/01",
      "CB代號": "25304",
      "CB名稱": "華建四",
      "外資_買張": 0,
      "外資_賣張": 0,
      "外資_買賣超": 0,
      "投信_買張": 0,
      "投信_賣張": 0,
      "投信_買賣超": 0,
      "自營_買張": 0,
      "自營_賣張": 42,
      "自營_買賣超": -42,
      "三大法人合計買賣超": -42,
      "買超方向": "↓賣超"
    },
    {
      "日期": "2026/07/01",
      "CB代號": "35832",
      "CB名稱": "辛耘二",
      "外資_買張": 0,
      "外資_賣張": 0,
      "外資_買賣超": 0,
      "投信_買張": 0,
      "投信_賣張": 0,
      "投信_買賣超": 0,
      "自營_買張": 18,
      "自營_賣張": 63,
      "自營_買賣超": -45,
      "三大法人合計買賣超": -45,
      "買超方向": "↓賣超"
    },
    {
      "日期": "2026/07/01",
      "CB代號": "23683",
      "CB名稱": "金像電三",
      "外資_買張": 0,
      "外資_賣張": 0,
      "外資_買賣超": 0,
      "投信_買張": 0,
      "投信_賣張": 0,
      "投信_買賣超": 0,
      "自營_買張": 78,
      "自營_賣張": 124,
      "自營_買賣超": -46,
      "三大法人合計買賣超": -46,
      "買超方向": "↓賣超"
    },
    {
      "日期": "2026/07/01",
      "CB代號": "24424",
      "CB名稱": "新美齊四",
      "外資_買張": 0,
      "外資_賣張": 0,
      "外資_買賣超": 0,
      "投信_買張": 0,
      "投信_賣張": 0,
      "投信_買賣超": 0,
      "自營_買張": 0,
      "自營_賣張": 50,
      "自營_買賣超": -50,
      "三大法人合計買賣超": -50,
      "買超方向": "↓賣超"
    },
    {
      "日期": "2026/07/01",
      "CB代號": "24361",
      "CB名稱": "偉詮電一",
      "外資_買張": 0,
      "外資_賣張": 0,
      "外資_買賣超": 0,
      "投信_買張": 0,
      "投信_賣張": 0,
      "投信_買賣超": 0,
      "自營_買張": 113,
      "自營_賣張": 163,
      "自營_買賣超": -50,
      "三大法人合計買賣超": -50,
      "買超方向": "↓賣超"
    },
    {
      "日期": "2026/07/01",
      "CB代號": "64145",
      "CB名稱": "樺漢五",
      "外資_買張": 0,
      "外資_賣張": 0,
      "外資_買賣超": 0,
      "投信_買張": 0,
      "投信_賣張": 0,
      "投信_買賣超": 0,
      "自營_買張": 79,
      "自營_賣張": 167,
      "自營_買賣超": -88,
      "三大法人合計買賣超": -88,
      "買超方向": "↓賣超"
    },
    {
      "日期": "2026/07/01",
      "CB代號": "32608",
      "CB名稱": "威剛八",
      "外資_買張": 0,
      "外資_賣張": 0,
      "外資_買賣超": 0,
      "投信_買張": 0,
      "投信_賣張": 0,
      "投信_買賣超": 0,
      "自營_買張": 41,
      "自營_賣張": 131,
      "自營_買賣超": -90,
      "三大法人合計買賣超": -90,
      "買超方向": "↓賣超"
    },
    {
      "日期": "2026/07/01",
      "CB代號": "76101",
      "CB名稱": "聯友金屬一創",
      "外資_買張": 0,
      "外資_賣張": 0,
      "外資_買賣超": 0,
      "投信_買張": 0,
      "投信_賣張": 0,
      "投信_買賣超": 0,
      "自營_買張": 0,
      "自營_賣張": 105,
      "自營_買賣超": -105,
      "三大法人合計買賣超": -105,
      "買超方向": "↓賣超"
    },
    {
      "日期": "2026/07/01",
      "CB代號": "33035",
      "CB名稱": "岱稜五",
      "外資_買張": 0,
      "外資_賣張": 0,
      "外資_買賣超": 0,
      "投信_買張": 0,
      "投信_賣張": 0,
      "投信_買賣超": 0,
      "自營_買張": 0,
      "自營_賣張": 108,
      "自營_買賣超": -108,
      "三大法人合計買賣超": -108,
      "買超方向": "↓賣超"
    },
    {
      "日期": "2026/07/01",
      "CB代號": "24642",
      "CB名稱": "盟立二",
      "外資_買張": 0,
      "外資_賣張": 0,
      "外資_買賣超": 0,
      "投信_買張": 0,
      "投信_賣張": 20,
      "投信_買賣超": -20,
      "自營_買張": 73,
      "自營_賣張": 164,
      "自營_買賣超": -91,
      "三大法人合計買賣超": -111,
      "買超方向": "↓賣超"
    },
    {
      "日期": "2026/07/01",
      "CB代號": "41904",
      "CB名稱": "佐登四KY",
      "外資_買張": 0,
      "外資_賣張": 0,
      "外資_買賣超": 0,
      "投信_買張": 0,
      "投信_賣張": 0,
      "投信_買賣超": 0,
      "自營_買張": 9,
      "自營_賣張": 131,
      "自營_買賣超": -122,
      "三大法人合計買賣超": -122,
      "買超方向": "↓賣超"
    },
    {
      "日期": "2026/07/01",
      "CB代號": "99587",
      "CB名稱": "世紀鋼七",
      "外資_買張": 0,
      "外資_賣張": 310,
      "外資_買賣超": -310,
      "投信_買張": 0,
      "投信_賣張": 0,
      "投信_買賣超": 0,
      "自營_買張": 0,
      "自營_賣張": 0,
      "自營_買賣超": 0,
      "三大法人合計買賣超": -310,
      "買超方向": "↓賣超"
    },
    {
      "日期": "2026/07/01",
      "CB代號": "37023",
      "CB名稱": "大聯大三",
      "外資_買張": 0,
      "外資_賣張": 0,
      "外資_買賣超": 0,
      "投信_買張": 0,
      "投信_賣張": 0,
      "投信_買賣超": 0,
      "自營_買張": 316,
      "自營_賣張": 750,
      "自營_買賣超": -434,
      "三大法人合計買賣超": -434,
      "買超方向": "↓賣超"
    },
    {
      "日期": "2026/07/01",
      "CB代號": "37022",
      "CB名稱": "大聯大二",
      "外資_買張": 0,
      "外資_賣張": 0,
      "外資_買賣超": 0,
      "投信_買張": 0,
      "投信_賣張": 0,
      "投信_買賣超": 0,
      "自營_買張": 489,
      "自營_賣張": 1520,
      "自營_買賣超": -1031,
      "三大法人合計買賣超": -1031,
      "買超方向": "↓賣超"
    }
  ]
}